bingenetic/__init__.py
bingenetic-2.6.dist-info/METADATA
bingenetic-2.6.dist-info/WHEEL
bingenetic-2.6.dist-info/top_level.txt
bingenetic-2.6.dist-info/RECORD
