Metadata-Version: 2.2
Name: bingenetic
Version: 2.6
Summary: BinGenetic is a lightweight Python library that enables seamless conversion between binary data and genetic sequences (DNA or RNA), facilitating research in DNA data storage and bioinformatics.
Home-page: https://github.com/mr-ravin/BinGenetic
Author: Ravin Kumar
Author-email: mr.ravin_kumar@hotmail.com
Keywords: Data Storage,DNA Data Storage,RNA Data Storage,Genetic Storage
Classifier: Programming Language :: Python :: 3
Classifier: License :: OSI Approved :: MIT License
Classifier: Operating System :: OS Independent
Requires-Python: >=3.7
Dynamic: author
Dynamic: author-email
Dynamic: classifier
Dynamic: description
Dynamic: description-content-type
Dynamic: home-page
Dynamic: keywords
Dynamic: requires-python
Dynamic: summary
